[
    {
        "offset":{
            "x":-3,
            "y":-3
        }
    },
    {
        "offset":{
            "x":0,
            "y":-3
        }
    },
    {
        "offset":{
            "x":3,
            "y":-3
        }
    }
    ,
    {
        "offset":{
            "x":-3,
            "y":0
        }
    },
    {
        "offset":{
            "x":0,
            "y":0
        }
    },
    {
        "offset":{
            "x":3,
            "y":0
        }
    },
    {
        "offset":{
            "x":-3,
            "y":3
        }
    },
    {
        "offset":{
            "x":0,
            "y":3
        }
    },
    {
        "offset":{
            "x":3,
            "y":3
        }
    },
    {
        "offset":{
            "x":6,
            "y":6
        }
    }
]